{
  "politics": [
    {
      "text": "The Prime Minister announced new economic policies aimed at reducing inflation and boosting employment across the nation.",
      "source": "Sample political news content",
      "date_collected": "2025-08-20T13:25:36.781586"
    },
    {
      "text": "Opposition parties criticized the government's handling of the recent budget crisis, calling for immediate reforms.",
      "source": "Sample political news content",
      "date_collected": "2025-08-20T13:25:36.781597"
    },
    {
      "text": "International diplomats gathered at the UN summit to discuss climate change agreements and global cooperation.",
      "source": "Sample political news content",
      "date_collected": "2025-08-20T13:25:36.781599"
    },
    {
      "text": "The election commission announced new voting procedures to ensure transparency in the upcoming general elections.",
      "source": "Sample political news content",
      "date_collected": "2025-08-20T13:25:36.781600"
    },
    {
      "text": "Senate passed the controversial healthcare reform bill after months of heated debate and negotiations.",
      "source": "Sample political news content",
      "date_collected": "2025-08-20T13:25:36.781601"
    },
    {
      "text": "The President's approval ratings have declined following recent foreign policy decisions in the Middle East.",
      "source": "Sample political news content",
      "date_collected": "2025-08-20T13:25:36.781602"
    },
    {
      "text": "Local government officials unveiled plans for infrastructure development in rural constituencies.",
      "source": "Sample political news content",
      "date_collected": "2025-08-20T13:25:36.781604"
    },
    {
      "text": "Political analysts predict major shifts in voter demographics ahead of the midterm elections.",
      "source": "Sample political news content",
      "date_collected": "2025-08-20T13:25:36.781605"
    },
    {
      "text": "The ruling party faces internal divisions over proposed constitutional amendments.",
      "source": "Sample political news content",
      "date_collected": "2025-08-20T13:25:36.781606"
    },
    {
      "text": "International sanctions were imposed following violations of human rights agreements.",
      "source": "Sample political news content",
      "date_collected": "2025-08-20T13:25:36.781607"
    },
    {
      "text": "Parliamentary sessions were disrupted as opposition members protested against new taxation policies.",
      "source": "Sample political news content",
      "date_collected": "2025-08-20T13:25:36.781608"
    },
    {
      "text": "The foreign minister embarked on a diplomatic tour to strengthen bilateral relations with neighboring countries.",
      "source": "Sample political news content",
      "date_collected": "2025-08-20T13:25:36.781609"
    },
    {
      "text": "Campaign finance reforms have been proposed to limit corporate influence in political elections.",
      "source": "Sample political news content",
      "date_collected": "2025-08-20T13:25:36.781610"
    },
    {
      "text": "The government announced emergency measures to address the ongoing refugee crisis at the borders.",
      "source": "Sample political news content",
      "date_collected": "2025-08-20T13:25:36.781611"
    },
    {
      "text": "Coalition talks between major political parties continue as no single party secured a majority.",
      "source": "Sample political news content",
      "date_collected": "2025-08-20T13:25:36.781612"
    },
    {
      "text": "The supreme court ruling on electoral boundaries has sparked nationwide political debates.",
      "source": "Sample political news content",
      "date_collected": "2025-08-20T13:25:36.781613"
    },
    {
      "text": "Ministers faced tough questions during the parliamentary inquiry into government spending.",
      "source": "Sample political news content",
      "date_collected": "2025-08-20T13:25:36.781615"
    },
    {
      "text": "Political tensions escalated following allegations of election fraud in several key districts.",
      "source": "Sample political news content",
      "date_collected": "2025-08-20T13:25:36.781616"
    },
    {
      "text": "The cabinet reshuffle saw several senior ministers replaced amid corruption investigations.",
      "source": "Sample political news content",
      "date_collected": "2025-08-20T13:25:36.781617"
    },
    {
      "text": "New legislation on data privacy rights passed through the lower house of parliament.",
      "source": "Sample political news content",
      "date_collected": "2025-08-20T13:25:36.781618"
    },
    {
      "text": "The governor signed an executive order addressing climate change mitigation strategies.",
      "source": "Sample political news content",
      "date_collected": "2025-08-20T13:25:36.781619"
    },
    {
      "text": "Political parties are mobilizing grassroots campaigns ahead of local council elections.",
      "source": "Sample political news content",
      "date_collected": "2025-08-20T13:25:36.781620"
    },
    {
      "text": "The attorney general launched an investigation into campaign finance violations.",
      "source": "Sample political news content",
      "date_collected": "2025-08-20T13:25:36.781621"
    },
    {
      "text": "Diplomatic relations strained following trade disputes between major economic powers.",
      "source": "Sample political news content",
      "date_collected": "2025-08-20T13:25:36.781622"
    },
    {
      "text": "The parliament voted to extend emergency powers amid ongoing security concerns.",
      "source": "Sample political news content",
      "date_collected": "2025-08-20T13:25:36.781623"
    },
    {
      "text": "Opposition leaders called for transparency in government procurement processes.",
      "source": "Sample political news content",
      "date_collected": "2025-08-20T13:25:36.781625"
    },
    {
      "text": "The electoral commission announced new guidelines for political advertising on social media.",
      "source": "Sample political news content",
      "date_collected": "2025-08-20T13:25:36.781626"
    },
    {
      "text": "International observers raised concerns about press freedom following recent media regulations.",
      "source": "Sample political news content",
      "date_collected": "2025-08-20T13:25:36.781627"
    },
    {
      "text": "The president's state of the union address focused on economic recovery and social justice.",
      "source": "Sample political news content",
      "date_collected": "2025-08-20T13:25:36.781628"
    },
    {
      "text": "Political deadlock continues as parties fail to agree on budget allocations.",
      "source": "Sample political news content",
      "date_collected": "2025-08-20T13:25:36.781629"
    },
    {
      "text": "The foreign ministry condemned military actions in the disputed border region.",
      "source": "Sample political news content",
      "date_collected": "2025-08-20T13:25:36.781630"
    },
    {
      "text": "Local elections saw record voter turnout amid heightened political awareness.",
      "source": "Sample political news content",
      "date_collected": "2025-08-20T13:25:36.781631"
    },
    {
      "text": "The government faces criticism over its response to recent civil unrest.",
      "source": "Sample political news content",
      "date_collected": "2025-08-20T13:25:36.781632"
    },
    {
      "text": "New anti-corruption legislation aims to increase accountability in public offices.",
      "source": "Sample political news content",
      "date_collected": "2025-08-20T13:25:36.781633"
    },
    {
      "text": "Political analysts debate the impact of social media on modern election campaigns.",
      "source": "Sample political news content",
      "date_collected": "2025-08-20T13:25:36.781635"
    }
  ],
  "business": [
    {
      "text": "Tech giant Apple reported record quarterly earnings, exceeding analyst expectations by 15 percent.",
      "source": "Sample business news content",
      "date_collected": "2025-08-20T13:25:36.781636"
    },
    {
      "text": "The stock market experienced significant volatility following Federal Reserve's interest rate announcement.",
      "source": "Sample business news content",
      "date_collected": "2025-08-20T13:25:36.781637"
    },
    {
      "text": "Amazon announced plans to expand its logistics network with 50 new distribution centers worldwide.",
      "source": "Sample business news content",
      "date_collected": "2025-08-20T13:25:36.781639"
    },
    {
      "text": "Small businesses struggle to adapt to new digital transformation requirements in the post-pandemic economy.",
      "source": "Sample business news content",
      "date_collected": "2025-08-20T13:25:36.781641"
    },
    {
      "text": "Oil prices surged to yearly highs amid supply chain disruptions and geopolitical tensions.",
      "source": "Sample business news content",
      "date_collected": "2025-08-20T13:25:36.781642"
    },
    {
      "text": "The merger between two pharmaceutical giants created the world's largest drug manufacturer.",
      "source": "Sample business news content",
      "date_collected": "2025-08-20T13:25:36.781643"
    },
    {
      "text": "Cryptocurrency markets faced regulatory scrutiny as governments worldwide implement new oversight measures.",
      "source": "Sample business news content",
      "date_collected": "2025-08-20T13:25:36.781644"
    },
    {
      "text": "Retail sales showed unexpected growth despite concerns about consumer spending and inflation.",
      "source": "Sample business news content",
      "date_collected": "2025-08-20T13:25:36.781645"
    },
    {
      "text": "The automotive industry shifts focus to electric vehicles with major investments in battery technology.",
      "source": "Sample business news content",
      "date_collected": "2025-08-20T13:25:36.781646"
    },
    {
      "text": "Global supply chains continue to face disruptions affecting manufacturing and distribution sectors.",
      "source": "Sample business news content",
      "date_collected": "2025-08-20T13:25:36.781647"
    },
    {
      "text": "The central bank's monetary policy decision impacts mortgage rates and housing market dynamics.",
      "source": "Sample business news content",
      "date_collected": "2025-08-20T13:25:36.781649"
    },
    {
      "text": "E-commerce platforms report unprecedented growth as consumer shopping habits permanently shift online.",
      "source": "Sample business news content",
      "date_collected": "2025-08-20T13:25:36.781650"
    },
    {
      "text": "Investment firms increase allocations to renewable energy projects amid climate change concerns.",
      "source": "Sample business news content",
      "date_collected": "2025-08-20T13:25:36.781651"
    },
    {
      "text": "The gig economy expands as more workers seek flexible employment opportunities.",
      "source": "Sample business news content",
      "date_collected": "2025-08-20T13:25:36.781652"
    },
    {
      "text": "Corporate earnings reports show mixed results across different sectors of the economy.",
      "source": "Sample business news content",
      "date_collected": "2025-08-20T13:25:36.781653"
    },
    {
      "text": "Startup valuations reach record highs despite concerns about market sustainability.",
      "source": "Sample business news content",
      "date_collected": "2025-08-20T13:25:36.781654"
    },
    {
      "text": "International trade agreements reshape global commerce patterns and supply chain strategies.",
      "source": "Sample business news content",
      "date_collected": "2025-08-20T13:25:36.781655"
    },
    {
      "text": "The banking sector implements new fintech solutions to improve customer service efficiency.",
      "source": "Sample business news content",
      "date_collected": "2025-08-20T13:25:36.781656"
    },
    {
      "text": "Manufacturing output increases as companies invest in automation and artificial intelligence.",
      "source": "Sample business news content",
      "date_collected": "2025-08-20T13:25:36.781657"
    },
    {
      "text": "Consumer confidence indices suggest optimistic outlook for economic recovery.",
      "source": "Sample business news content",
      "date_collected": "2025-08-20T13:25:36.781659"
    },
    {
      "text": "The real estate market experiences cooling after years of unprecedented growth.",
      "source": "Sample business news content",
      "date_collected": "2025-08-20T13:25:36.781660"
    },
    {
      "text": "Technology companies face antitrust investigations over market dominance concerns.",
      "source": "Sample business news content",
      "date_collected": "2025-08-20T13:25:36.781661"
    },
    {
      "text": "Venture capital funding reaches new heights in biotechnology and healthcare sectors.",
      "source": "Sample business news content",
      "date_collected": "2025-08-20T13:25:36.781662"
    },
    {
      "text": "The hospitality industry shows signs of recovery as travel restrictions ease globally.",
      "source": "Sample business news content",
      "date_collected": "2025-08-20T13:25:36.781663"
    },
    {
      "text": "Agricultural commodities prices fluctuate due to weather patterns and climate change.",
      "source": "Sample business news content",
      "date_collected": "2025-08-20T13:25:36.781664"
    },
    {
      "text": "Financial markets react to inflation data and economic growth projections.",
      "source": "Sample business news content",
      "date_collected": "2025-08-20T13:25:36.781665"
    },
    {
      "text": "Corporate restructuring efforts aim to improve operational efficiency and profitability.",
      "source": "Sample business news content",
      "date_collected": "2025-08-20T13:25:36.781667"
    },
    {
      "text": "The renewable energy sector attracts significant investment from institutional investors.",
      "source": "Sample business news content",
      "date_collected": "2025-08-20T13:25:36.781668"
    },
    {
      "text": "Retail chains adapt business models to compete with online marketplace dominance.",
      "source": "Sample business news content",
      "date_collected": "2025-08-20T13:25:36.781669"
    },
    {
      "text": "The semiconductor shortage continues to impact various industries worldwide.",
      "source": "Sample business news content",
      "date_collected": "2025-08-20T13:25:36.781670"
    },
    {
      "text": "Private equity firms increase acquisition activity in healthcare and technology sectors.",
      "source": "Sample business news content",
      "date_collected": "2025-08-20T13:25:36.781671"
    },
    {
      "text": "The sharing economy model expands into new markets and service categories.",
      "source": "Sample business news content",
      "date_collected": "2025-08-20T13:25:36.781673"
    },
    {
      "text": "Corporate sustainability initiatives drive changes in business practices and reporting.",
      "source": "Sample business news content",
      "date_collected": "2025-08-20T13:25:36.781674"
    },
    {
      "text": "International currency fluctuations affect multinational corporation profit margins.",
      "source": "Sample business news content",
      "date_collected": "2025-08-20T13:25:36.781675"
    },
    {
      "text": "The insurance industry adapts to climate change risks and emerging technologies.",
      "source": "Sample business news content",
      "date_collected": "2025-08-20T13:25:36.781676"
    }
  ],
  "health": [
    {
      "text": "Researchers discovered a breakthrough treatment for Alzheimer's disease showing promising clinical trial results.",
      "source": "Sample health news content",
      "date_collected": "2025-08-20T13:25:36.781677"
    },
    {
      "text": "The World Health Organization issued new guidelines for preventing the spread of infectious diseases.",
      "source": "Sample health news content",
      "date_collected": "2025-08-20T13:25:36.781678"
    },
    {
      "text": "Mental health awareness campaigns highlight the importance of seeking professional help for depression and anxiety.",
      "source": "Sample health news content",
      "date_collected": "2025-08-20T13:25:36.781679"
    },
    {
      "text": "New study reveals the long-term effects of COVID-19 on cardiovascular and respiratory systems.",
      "source": "Sample health news content",
      "date_collected": "2025-08-20T13:25:36.781680"
    },
    {
      "text": "Hospitals implement telemedicine services to improve healthcare accessibility in rural areas.",
      "source": "Sample health news content",
      "date_collected": "2025-08-20T13:25:36.781682"
    },
    {
      "text": "Vaccination campaigns successfully reduced measles cases by 80 percent in developing countries.",
      "source": "Sample health news content",
      "date_collected": "2025-08-20T13:25:36.781684"
    },
    {
      "text": "Scientists develop new gene therapy techniques for treating rare genetic disorders.",
      "source": "Sample health news content",
      "date_collected": "2025-08-20T13:25:36.781685"
    },
    {
      "text": "Public health officials warn about the rising obesity rates and associated health complications.",
      "source": "Sample health news content",
      "date_collected": "2025-08-20T13:25:36.781686"
    },
    {
      "text": "Medical researchers identify potential biomarkers for early cancer detection and diagnosis.",
      "source": "Sample health news content",
      "date_collected": "2025-08-20T13:25:36.781687"
    },
    {
      "text": "The healthcare system faces challenges in addressing the growing elderly population's needs.",
      "source": "Sample health news content",
      "date_collected": "2025-08-20T13:25:36.781688"
    },
    {
      "text": "New dietary guidelines emphasize the importance of plant-based foods for heart health.",
      "source": "Sample health news content",
      "date_collected": "2025-08-20T13:25:36.781689"
    },
    {
      "text": "Clinical trials begin for innovative immunotherapy treatments targeting autoimmune diseases.",
      "source": "Sample health news content",
      "date_collected": "2025-08-20T13:25:36.781690"
    },
    {
      "text": "Mental health services expand to include digital therapy platforms and mobile applications.",
      "source": "Sample health news content",
      "date_collected": "2025-08-20T13:25:36.781691"
    },
    {
      "text": "Antibiotic resistance poses significant challenges to treating bacterial infections globally.",
      "source": "Sample health news content",
      "date_collected": "2025-08-20T13:25:36.781693"
    },
    {
      "text": "Healthcare providers implement artificial intelligence tools for improved diagnostic accuracy.",
      "source": "Sample health news content",
      "date_collected": "2025-08-20T13:25:36.781756"
    },
    {
      "text": "Public health campaigns focus on reducing tobacco use and promoting smoking cessation.",
      "source": "Sample health news content",
      "date_collected": "2025-08-20T13:25:36.781758"
    },
    {
      "text": "Researchers investigate the gut microbiome's role in overall health and disease prevention.",
      "source": "Sample health news content",
      "date_collected": "2025-08-20T13:25:36.781759"
    },
    {
      "text": "New surgical techniques using robotics improve patient outcomes and recovery times.",
      "source": "Sample health news content",
      "date_collected": "2025-08-20T13:25:36.781760"
    },
    {
      "text": "The opioid crisis continues to impact communities, prompting new treatment approaches.",
      "source": "Sample health news content",
      "date_collected": "2025-08-20T13:25:36.781761"
    },
    {
      "text": "Preventive healthcare measures show effectiveness in reducing chronic disease incidence.",
      "source": "Sample health news content",
      "date_collected": "2025-08-20T13:25:36.781763"
    },
    {
      "text": "Medical breakthroughs in regenerative medicine offer hope for organ transplant patients.",
      "source": "Sample health news content",
      "date_collected": "2025-08-20T13:25:36.781764"
    },
    {
      "text": "Healthcare disparities persist in underserved communities despite policy interventions.",
      "source": "Sample health news content",
      "date_collected": "2025-08-20T13:25:36.781765"
    },
    {
      "text": "Nutrition studies reveal the benefits of Mediterranean diet for longevity and wellness.",
      "source": "Sample health news content",
      "date_collected": "2025-08-20T13:25:36.781766"
    },
    {
      "text": "Emergency medical services adapt protocols to handle pandemic-related challenges.",
      "source": "Sample health news content",
      "date_collected": "2025-08-20T13:25:36.781767"
    },
    {
      "text": "Personalized medicine approaches revolutionize cancer treatment strategies.",
      "source": "Sample health news content",
      "date_collected": "2025-08-20T13:25:36.781768"
    },
    {
      "text": "Sleep disorders affect millions, leading to increased focus on sleep health education.",
      "source": "Sample health news content",
      "date_collected": "2025-08-20T13:25:36.781769"
    },
    {
      "text": "Maternal and child health programs show improvements in infant mortality rates.",
      "source": "Sample health news content",
      "date_collected": "2025-08-20T13:25:36.781770"
    },
    {
      "text": "Healthcare technology innovations streamline patient care and medical record management.",
      "source": "Sample health news content",
      "date_collected": "2025-08-20T13:25:36.781771"
    },
    {
      "text": "Environmental health concerns rise as pollution impacts respiratory disease rates.",
      "source": "Sample health news content",
      "date_collected": "2025-08-20T13:25:36.781772"
    },
    {
      "text": "Medical education evolves to include training in digital health technologies.",
      "source": "Sample health news content",
      "date_collected": "2025-08-20T13:25:36.781773"
    },
    {
      "text": "Preventive screening programs detect diseases earlier, improving treatment outcomes.",
      "source": "Sample health news content",
      "date_collected": "2025-08-20T13:25:36.781774"
    },
    {
      "text": "Healthcare costs continue to rise, prompting discussions about system reforms.",
      "source": "Sample health news content",
      "date_collected": "2025-08-20T13:25:36.781776"
    },
    {
      "text": "Research advances in neuroscience provide insights into brain function and disorders.",
      "source": "Sample health news content",
      "date_collected": "2025-08-20T13:25:36.781777"
    },
    {
      "text": "Global health initiatives address infectious disease outbreaks in developing regions.",
      "source": "Sample health news content",
      "date_collected": "2025-08-20T13:25:36.781778"
    },
    {
      "text": "Fitness and wellness trends emphasize holistic approaches to health maintenance.",
      "source": "Sample health news content",
      "date_collected": "2025-08-20T13:25:36.781779"
    }
  ]
}